LICENSE
MANIFEST.in
Makefile
README.rst
setup.py
detools/__init__.py
detools/__main__.py
detools/apply.py
detools/bsdiff.c
detools/common.py
detools/create.py
detools/errors.py
detools/hdiffpatch.cpp
detools/info.py
detools/suffix_array.c
detools/version.py
detools.egg-info/PKG-INFO
detools.egg-info/SOURCES.txt
detools.egg-info/dependency_links.txt
detools.egg-info/entry_points.txt
detools.egg-info/requires.txt
detools.egg-info/top_level.txt
detools/HDiffPatch/_atosize.h
detools/HDiffPatch/_clock_for_demo.h
detools/HDiffPatch/checksum_plugin_demo.h
detools/HDiffPatch/compress_parallel.cpp
detools/HDiffPatch/compress_parallel.h
detools/HDiffPatch/compress_plugin_demo.h
detools/HDiffPatch/decompress_plugin_demo.h
detools/HDiffPatch/file_for_patch.c
detools/HDiffPatch/file_for_patch.h
detools/HDiffPatch/hdiffz.cpp
detools/HDiffPatch/hpatch_dir_listener.h
detools/HDiffPatch/hpatchz.c
detools/HDiffPatch/builds/android_ndk_jni_mk/hpatch.c
detools/HDiffPatch/builds/android_ndk_jni_mk/hpatch.h
detools/HDiffPatch/builds/android_ndk_jni_mk/hpatch_jni.c
detools/HDiffPatch/dirDiffPatch/dir_diff/dir_diff.cpp
detools/HDiffPatch/dirDiffPatch/dir_diff/dir_diff.h
detools/HDiffPatch/dirDiffPatch/dir_diff/file_for_dirDiff.h
detools/HDiffPatch/dirDiffPatch/dir_patch/dir_patch.c
detools/HDiffPatch/dirDiffPatch/dir_patch/dir_patch.h
detools/HDiffPatch/dirDiffPatch/dir_patch/dir_patch_private.h
detools/HDiffPatch/dirDiffPatch/dir_patch/dir_patch_types.h
detools/HDiffPatch/dirDiffPatch/dir_patch/new_stream.c
detools/HDiffPatch/dirDiffPatch/dir_patch/new_stream.h
detools/HDiffPatch/dirDiffPatch/dir_patch/ref_stream.c
detools/HDiffPatch/dirDiffPatch/dir_patch/ref_stream.h
detools/HDiffPatch/dirDiffPatch/dir_patch/res_handle_limit.c
detools/HDiffPatch/dirDiffPatch/dir_patch/res_handle_limit.h
detools/HDiffPatch/libHDiffPatch/HDiff/diff.cpp
detools/HDiffPatch/libHDiffPatch/HDiff/diff.h
detools/HDiffPatch/libHDiffPatch/HDiff/diff_types.h
detools/HDiffPatch/libHDiffPatch/HDiff/private_diff/bytes_rle.cpp
detools/HDiffPatch/libHDiffPatch/HDiff/private_diff/bytes_rle.h
detools/HDiffPatch/libHDiffPatch/HDiff/private_diff/compress_detect.cpp
