Metadata-Version: 2.1
Name: detools
Version: 0.53.0
Summary: Binary delta encoding tools.
Home-page: https://github.com/eerimoq/detools
Author: Erik Moqvist
Author-email: erik.moqvist@gmail.com
License: BSD
Classifier: License :: OSI Approved :: BSD License
Classifier: Programming Language :: Python :: 3
License-File: LICENSE
